Metadata-Version: 2.1
Name: hamas-rocket
Version: 1.2.0
Summary: An awesome package that does something
Home-page: http://pypi.python.org/pypi/hamas_rocket/
Author: Kassam
Author-email: ca.atallah@esi-sba.dz
License: LICENSE.txt
Platform: UNKNOWN
